<?xml version="1.0" encoding="utf-8"?>
<AssetDeclaration xmlns="uri:ea.com:eala:asset" xmlns:xsi="http://www.w3.org/2001/XMLSchema-instance" xmlns:xi="http://www.w3.org/2001/XInclude">
	<Tags></Tags>
	<Includes>
		<Include
			type="all"
			source="ART:SS_FlingCone.w3x" />
		<Include
			type="instance"
			source="DATA:EP1/Neutral/Props/BaseClientFlingableProp.xml" />
	</Includes>
	<GameObject
		id="SS_FlingCone"
		inheritFrom="BaseClientFlingableProp"
		Side="Civilian"
		EditorName="SS_FlingCone"
		KindOf="+SELECTABLE"
		Browser="REGION Shiro_Sanitarium_SS DESTRUCTIBLE_PROPS" >

		<Draws>

			<ScriptedModelDraw
				id="ModuleTag_Draw"
				OkToChangeModelColor="true">
				<ModelConditionState
					ParseCondStateType="PARSE_DEFAULT">
					<Model
						Name="SS_FlingCone" />
				</ModelConditionState>
			</ScriptedModelDraw>
      
		</Draws>
		<Behaviors>

			<DynamicsUpdate
				id="DynamicsUpdate"
				Motion="SIMULATED"
				Collision="INTERCOLLIDING"
				ContactTag="PROP">
				<Volume Mass="2529" Spinniness="10000.0" AngularDrag="0.01" LinearDrag="0.01" ContactTag="PROP" ReportContacts="true" >

	<Box  HalfSizeX="2.5" HalfSizeY="2.5" HalfSizeZ="4.0" >
		<Translation x="0.045" y="0.0" z="4.0" />
		<Rotation x="0.0" y="0.0" z="0.0" w="1.0" />
	</Box>

				</Volume>
			</DynamicsUpdate>

		</Behaviors>
		<Geometry
			IsSmall="true">
      <Shape
           Type= "BOX"
           MajorRadius = "2.5"
           MinorRadius = "2.5"
           Height = "8.09673"
           ContactPointGeneration = "NONE" >
        <Offset
            x = "0.0451121"
            y = "-0.00476074"
            z = "0.0" />
      </Shape>

		</Geometry>
	</GameObject>
</AssetDeclaration>
