<?xml version="1.0" encoding="us-ascii"?>
<AssetDeclaration xmlns="uri:ea.com:eala:asset" xmlns:xsi="http://www.w3.org/2001/XMLSchema-instance">
	<Tags></Tags>
	<Includes>
    <Include
		type="all"
		source="ART:NY_Structure_02_COL.w3x" />
    <Include
		type="instance"
		source="DATA:BaseObjects/BaseCollapsingObject.xml" />
	</Includes>
	<GameObject
		id="NY_Structure_02_Collapse"
		inheritFrom="BaseCollapsingObject" 
		EditorName="NY_Structure_02_Collapse">
		<Draws>
			<DynamicsDraw 
			id="ModuleTag_Draw" 
			Collision="NONINTERCOLLIDING"
			DrawPriority="MUST_BE_DRAWN"
			FlingPerturbation="5"
			Explodiness="0.5">
			<ModelConditionState
				ParseCondStateType="PARSE_DEFAULT">
				<Model
					Name="NY_Structure_02_COL" />
			</ModelConditionState>
			<BoneVolumes>
			
<BoneVolume BoneName="Bone_D_01" Mass="47193" Spinniness="3.0" ContactTag="DEBRIS" >
	<Box  HalfSizeX="16.296" HalfSizeY="15.268" HalfSizeZ="9.484" >
		<Translation x="84.154" y="9.655" z="56.417" />
		<Rotation x="-0.706758" y="0.0104362" z="0.0024089" w="0.707374" />
	</Box>
</BoneVolume>
<BoneVolume BoneName="Bone_D_02" Mass="47222" Spinniness="3.0" ContactTag="DEBRIS" >
	<Box  HalfSizeX="17.122" HalfSizeY="14.05" HalfSizeZ="9.815" >
		<Translation x="-83.34" y="-11.167" z="51.253" />
		<Rotation x="-0.705927" y="0.000303878" z="-9.17485e-006" w="0.708284" />
	</Box>
</BoneVolume>
<BoneVolume BoneName="Bone_D_03" Mass="86068" Spinniness="3.0" ContactTag="DEBRIS" >
	<Box  HalfSizeX="29.011" HalfSizeY="12.536" HalfSizeZ="11.833" >
		<Translation x="16.787" y="-15.441" z="63.426" />
		<Rotation x="0.498431" y="0.501564" z="-0.507185" w="0.492711" />
	</Box>
</BoneVolume>
<BoneVolume BoneName="Bone_D_04" Mass="51959" Spinniness="3.0" ContactTag="DEBRIS" >
	<Box  HalfSizeX="22.691" HalfSizeY="12.528" HalfSizeZ="9.139" >
		<Translation x="16.293" y="12.359" z="21.139" />
		<Rotation x="-0.00338806" y="-0.0109425" z="0.00405157" w="0.999926" />
	</Box>
</BoneVolume>
<BoneVolume BoneName="Bone_D_05" Mass="3663" Spinniness="3.0" ContactTag="DEBRIS" >
	<Box  HalfSizeX="17.035" HalfSizeY="0.943" HalfSizeZ="11.403" >
		<Translation x="-24.936" y="-21.071" z="16.886" />
		<Rotation x="-0.00872649" y="5.86509e-006" z="-0.000672076" w="0.999962" />
	</Box>
</BoneVolume>
<BoneVolume BoneName="Bone_D_06" Mass="49685" Spinniness="3.0" ContactTag="DEBRIS" >
	<Box  HalfSizeX="18.535" HalfSizeY="12.335" HalfSizeZ="10.866" >
		<Translation x="-94.464" y="0.526" z="23.958" />
		<Rotation x="-0.00525258" y="0.00019568" z="0.0012249" w="0.999985" />
	</Box>
</BoneVolume>
<BoneVolume BoneName="Bone_D_07" Mass="41004" Spinniness="3.0" ContactTag="DEBRIS" >
	<Box  HalfSizeX="17.643" HalfSizeY="12.001" HalfSizeZ="9.683" >
		<Translation x="101.171" y="-0.956" z="22.986" />
		<Rotation x="-0.516643" y="0.482784" z="-0.482783" w="0.516643" />
	</Box>
</BoneVolume>
<BoneVolume BoneName="Bone_D_08" Mass="3756" Spinniness="3.0" ContactTag="DEBRIS" >
	<Box  HalfSizeX="18.337" HalfSizeY="0.716" HalfSizeZ="14.304" >
		<Translation x="-24.787" y="-19.547" z="54.615" />
		<Rotation x="-0.00872633" y="5.27355e-005" z="-0.00604293" w="0.999944" />
	</Box>
</BoneVolume>
<BoneVolume BoneName="Bone_D_09" Mass="38152" Spinniness="3.0" ContactTag="DEBRIS" >
	<Box  HalfSizeX="18.398" HalfSizeY="11.118" HalfSizeZ="9.326" >
		<Translation x="96.314" y="-13.579" z="55.62" />
		<Rotation x="-0.00212055" y="0.000377819" z="0.000148159" w="0.999998" />
	</Box>
</BoneVolume>
<BoneVolume BoneName="Bone_D_10" Mass="17645" Spinniness="3.0" ContactTag="DEBRIS" >
	<Box  HalfSizeX="13.997" HalfSizeY="8.148" HalfSizeZ="7.736" >
		<Translation x="75.809" y="0.124" z="6.256" />
		<Rotation x="-0.70708" y="0.00618758" z="-0.00618758" w="0.70708" />
	</Box>
</BoneVolume>
<BoneVolume BoneName="Bone_D_11" Mass="32919" Spinniness="3.0" ContactTag="DEBRIS" >
	<Box  HalfSizeX="20.325" HalfSizeY="8.999" HalfSizeZ="8.999" >
		<Translation x="7.608" y="-11.086" z="5.678" />
		<Rotation x="-0.00575847" y="1.65836e-005" z="-0.00287981" w="0.999979" />
	</Box>
</BoneVolume>
<BoneVolume BoneName="Bone_D_12" Mass="6388" Spinniness="3.0" ContactTag="DEBRIS" >
	<Box  HalfSizeX="16.955" HalfSizeY="1.655" HalfSizeZ="11.383" >
		<Translation x="-24.934" y="19.761" z="16.863" />
		<Rotation x="0.0" y="0.0" z="0.0" w="1.0" />
	</Box>
</BoneVolume>
<BoneVolume BoneName="Bone_D_13" Mass="43376" Spinniness="3.0" ContactTag="DEBRIS" >
	<Box  HalfSizeX="19.317" HalfSizeY="10.596" HalfSizeZ="10.596" >
		<Translation x="-82.758" y="6.863" z="1.611" />
		<Rotation x="-0.707083" y="-0.00584441" z="0.00584441" w="0.707083" />
	</Box>
</BoneVolume>
<BoneVolume BoneName="Bone_D_14" Mass="44376" Spinniness="3.0" ContactTag="DEBRIS" >
	<Box  HalfSizeX="19.858" HalfSizeY="9.507" HalfSizeZ="11.753" >
		<Translation x="-83.986" y="11.561" z="51.009" />
		<Rotation x="-0.0174519" y="0.000111704" z="-0.00639957" w="0.999827" />
	</Box>
</BoneVolume>
<BoneVolume BoneName="Bone_D_15" Mass="35246" Spinniness="3.0" ContactTag="DEBRIS" >
	<Box  HalfSizeX="16.784" HalfSizeY="7.385" HalfSizeZ="14.218" >
		<Translation x="-24.682" y="10.861" z="54.415" />
		<Rotation x="0.0" y="0.0" z="0.0" w="1.0" />
	</Box>
</BoneVolume>
<BoneVolume BoneName="Bone_D_16" Mass="15423" Spinniness="3.0" ContactTag="DEBRIS" >
	<Box  HalfSizeX="13.84" HalfSizeY="9.647" HalfSizeZ="5.776" >
		<Translation x="22.07" y="12.442" z="86.92" />
		<Rotation x="-0.707079" y="0.00629969" z="-0.00629969" w="0.707079" />
	</Box>
</BoneVolume>
<BoneVolume BoneName="Bone_D_17" Mass="15543" Spinniness="3.0" ContactTag="DEBRIS" >
	<Box  HalfSizeX="13.563" HalfSizeY="10.122" HalfSizeZ="5.661" >
		<Translation x="-23.726" y="12.637" z="86.918" />
		<Rotation x="-0.00191164" y="9.30028e-005" z="4.92921e-005" w="0.999998" />
	</Box>
</BoneVolume>
<BoneVolume BoneName="Bone_D_18" Mass="58393" Spinniness="3.0" ContactTag="DEBRIS" >
	<Box  HalfSizeX="21.545" HalfSizeY="15.616" HalfSizeZ="8.678" >
		<Translation x="14.661" y="11.801" z="52.01" />
		<Rotation x="-0.707001" y="0.0122253" z="-0.0122253" w="0.707001" />
	</Box>
</BoneVolume>
<BoneVolume BoneName="Bone_D_19" Mass="17417" Spinniness="3.0" ContactTag="DEBRIS" >
	<Box  HalfSizeX="15.376" HalfSizeY="6.361" HalfSizeZ="8.904" >
		<Translation x="-26.372" y="-12.669" z="86.916" />
		<Rotation x="-0.704637" y="0.00120367" z="-0.00262574" w="0.709562" />
	</Box>
</BoneVolume>


			</BoneVolumes>
			<Lifetime
				Delay="5s"
				FadeTime="4s" />
		</DynamicsDraw>
	</Draws>
	<Behaviors/>
</GameObject>
</AssetDeclaration>
