<?xml version="1.0" encoding="us-ascii"?>
<AssetDeclaration xmlns="uri:ea.com:eala:asset" xmlns:xsi="http://www.w3.org/2001/XMLSchema-instance">
	<Tags></Tags>
	<Includes>
    <Include
		type="all"
		source="ART:FI_Structure_08_COL.w3x" />
    <Include
		type="instance"
		source="DATA:BaseObjects/BaseCollapsingObject.xml" />
	</Includes>
	<GameObject
		id="FI_Structure_08_Collapse"
		inheritFrom="BaseCollapsingObject" 
		EditorName="FI_Structure_08_Collapse">
		<Draws>
			<DynamicsDraw 
			id="ModuleTag_Draw" 
			Collision="NONINTERCOLLIDING"
			DrawPriority="MUST_BE_DRAWN"
			FlingPerturbation="5"
			Explodiness="0.5">
			<ModelConditionState
				ParseCondStateType="PARSE_DEFAULT">
				<Model
					Name="FI_Structure_08_COL" />
			</ModelConditionState>
			<BoneVolumes>
			
<BoneVolume BoneName="Bone_D_01" Mass="32246" Spinniness="3.0" ContactTag="DEBRIS" >
	<Box  HalfSizeX="7.998" HalfSizeY="13.599" HalfSizeZ="14.824" >
		<Translation x="-16.946" y="17.124" z="51.452" />
		<Rotation x="-0.00148518" y="-0.00367595" z="-0.374604" w="0.927177" />
	</Box>
</BoneVolume>
<BoneVolume BoneName="Bone_D_02" Mass="28837" Spinniness="3.0" ContactTag="DEBRIS" >
	<Box  HalfSizeX="4.136" HalfSizeY="10.933" HalfSizeZ="31.887" >
		<Translation x="10.484" y="-9.017" z="97.795" />
		<Rotation x="-0.0598649" y="-0.144527" z="-0.377972" w="0.912505" />
	</Box>
</BoneVolume>
<BoneVolume BoneName="Bone_D_03" Mass="842039" Spinniness="3.0" ContactTag="DEBRIS" >
	<Box  HalfSizeX="45.517" HalfSizeY="31.9" HalfSizeZ="28.996" >
		<Translation x="-2.978" y="20.392" z="14.684" />
		<Rotation x="-0.666548" y="0.236037" z="-0.236037" w="0.666548" />
	</Box>
</BoneVolume>
<BoneVolume BoneName="Bone_D_04" Mass="117502" Spinniness="3.0" ContactTag="DEBRIS" >
	<Box  HalfSizeX="23.759" HalfSizeY="19.02" HalfSizeZ="13.001" >
		<Translation x="-6.975" y="-18.223" z="45.316" />
		<Rotation x="-0.00839496" y="0.00238232" z="-0.00274382" w="0.999958" />
	</Box>
</BoneVolume>
<BoneVolume BoneName="Bone_D_05" Mass="60609" Spinniness="3.0" ContactTag="DEBRIS" >
	<Box  HalfSizeX="18.703" HalfSizeY="13.326" HalfSizeZ="12.159" >
		<Translation x="19.339" y="19.3" z="51.428" />
		<Rotation x="-0.00239835" y="-0.00579013" z="-0.382676" w="0.923861" />
	</Box>
</BoneVolume>
<BoneVolume BoneName="Bone_D_06" Mass="22567" Spinniness="3.0" ContactTag="DEBRIS" >
	<Box  HalfSizeX="16.51" HalfSizeY="6.891" HalfSizeZ="9.918" >
		<Translation x="-2.122" y="9.866" z="66.586" />
		<Rotation x="-0.0117159" y="-0.00387698" z="-0.00533329" w="0.99991" />
	</Box>
</BoneVolume>
<BoneVolume BoneName="Bone_D_07" Mass="27589" Spinniness="3.0" ContactTag="DEBRIS" >
	<Box  HalfSizeX="8.838" HalfSizeY="10.36" HalfSizeZ="15.066" >
		<Translation x="41.94" y="15.181" z="13.911" />
		<Rotation x="0.0" y="0.000701496" z="0.0" w="1.0" />
	</Box>
</BoneVolume>
<BoneVolume BoneName="Bone_D_08" Mass="83536" Spinniness="3.0" ContactTag="DEBRIS" >
	<Box  HalfSizeX="18.634" HalfSizeY="18.611" HalfSizeZ="12.044" >
		<Translation x="19.551" y="-19.423" z="49.216" />
		<Rotation x="0.259114" y="0.642012" z="-0.281709" w="0.66432" />
	</Box>
</BoneVolume>
<BoneVolume BoneName="Bone_D_09" Mass="40631" Spinniness="3.0" ContactTag="DEBRIS" >
	<Box  HalfSizeX="9.757" HalfSizeY="8.98" HalfSizeZ="23.187" >
		<Translation x="10.921" y="12.255" z="90.049" />
		<Rotation x="0.0588109" y="-0.0493807" z="-0.353795" w="0.932165" />
	</Box>
</BoneVolume>
<BoneVolume BoneName="Bone_D_10" Mass="52175" Spinniness="3.0" ContactTag="DEBRIS" >
	<Box  HalfSizeX="14.172" HalfSizeY="19.042" HalfSizeZ="9.667" >
		<Translation x="-11.684" y="-10.23" z="101.909" />
		<Rotation x="-0.754304" y="0.336947" z="-0.229812" w="0.514469" />
	</Box>
</BoneVolume>
<BoneVolume BoneName="Bone_D_11" Mass="90792" Spinniness="3.0" ContactTag="DEBRIS" >
	<Box  HalfSizeX="26.437" HalfSizeY="17.168" HalfSizeZ="10.002" >
		<Translation x="-1.659" y="15.649" z="46.486" />
		<Rotation x="-0.0075432" y="0.00438766" z="0.00323529" w="0.999957" />
	</Box>
</BoneVolume>
<BoneVolume BoneName="Bone_D_12" Mass="76198" Spinniness="3.0" ContactTag="DEBRIS" >
	<Box  HalfSizeX="35.088" HalfSizeY="8.427" HalfSizeZ="12.885" >
		<Translation x="-1.65" y="-42.006" z="14.149" />
		<Rotation x="-0.0261759" y="-0.00872353" z="0.000228435" w="0.999619" />
	</Box>
</BoneVolume>
<BoneVolume BoneName="Bone_D_13" Mass="120730" Spinniness="3.0" ContactTag="DEBRIS" >
	<Box  HalfSizeX="14.541" HalfSizeY="27.469" HalfSizeZ="15.113" >
		<Translation x="28.672" y="-26.357" z="15.394" />
		<Rotation x="-0.261143" y="-0.657118" z="-0.279997" w="0.649309" />
	</Box>
</BoneVolume>
<BoneVolume BoneName="Bone_D_14" Mass="30007" Spinniness="3.0" ContactTag="DEBRIS" >
	<Box  HalfSizeX="9.485" HalfSizeY="10.962" HalfSizeZ="14.43" >
		<Translation x="-10.038" y="7.22" z="105.073" />
		<Rotation x="0.196657" y="0.0761716" z="0.353061" w="0.911522" />
	</Box>
</BoneVolume>
<BoneVolume BoneName="Bone_D_15" Mass="17494" Spinniness="3.0" ContactTag="DEBRIS" >
	<Box  HalfSizeX="14.676" HalfSizeY="7.563" HalfSizeZ="7.881" >
		<Translation x="0.275" y="-11.123" z="66.556" />
		<Rotation x="0.0" y="0.0" z="-0.381593" w="0.92433" />
	</Box>
</BoneVolume>
<BoneVolume BoneName="Bone_D_16" Mass="38683" Spinniness="3.0" ContactTag="DEBRIS" >
	<Box  HalfSizeX="19.29" HalfSizeY="8.218" HalfSizeZ="12.201" >
		<Translation x="16.78" y="41.928" z="14.833" />
		<Rotation x="0.0" y="0.0" z="-0.00664638" w="0.999978" />
	</Box>
</BoneVolume>
<BoneVolume BoneName="Bone_D_17" Mass="22719" Spinniness="3.0" ContactTag="DEBRIS" >
	<Box  HalfSizeX="9.026" HalfSizeY="10.315" HalfSizeZ="12.201" >
		<Translation x="-41.671" y="-15.169" z="15.548" />
		<Rotation x="0.0" y="0.0" z="0.0" w="1.0" />
	</Box>
</BoneVolume>
<BoneVolume BoneName="Bone_D_18" Mass="38799" Spinniness="3.0" ContactTag="DEBRIS" >
	<Box  HalfSizeX="9.025" HalfSizeY="12.201" HalfSizeZ="17.618" >
		<Translation x="-41.587" y="20.912" z="15.551" />
		<Rotation x="-0.70708" y="-0.00617059" z="0.00617059" w="0.70708" />
	</Box>
</BoneVolume>


			</BoneVolumes>
			<Lifetime
				Delay="5s"
				FadeTime="4s" />
		</DynamicsDraw>
	</Draws>
	<Behaviors/>
</GameObject>
</AssetDeclaration>
