<?xml version="1.0" encoding="utf-8"?>
<AssetDeclaration xmlns="uri:ea.com:eala:asset" xmlns:xsi="http://www.w3.org/2001/XMLSchema-instance">
	<Tags></Tags>
	<Includes>
		<Include
			type="instance"
			source="DATA:BaseObjects/BaseRockBig.xml" />
		<Include
			type="all"
			source="ART:CS_BeachWallRamp.W3X" />
	</Includes>
	<GameObject
		id="CS_BeachWallRamp"
		inheritFrom="BaseRockBig"
    KindOf="+CAN_BUILD_ON_WATER"
		EditorName="CS_BeachWallRamp"
		EditorSorting="OPTIMIZED_PROPS"
		Browser="REGION Cannes_CA OPTIMIZED_PROPS">
	
		<Draws>
			<ScriptedModelDraw
				id="ModuleTag_Draw"
				OkToChangeModelColor="true">
				<ModelConditionState
					ParseCondStateType="PARSE_DEFAULT">
					<Model
						Name="CS_BeachWallRamp" />
				</ModelConditionState>
			</ScriptedModelDraw>
		</Draws>
		
		<Geometry
			IsSmall="false">
      <Shape
           Type= "BOX"
           MajorRadius = "65.4037"
           MinorRadius = "9.64181"
           Height = "13.5784"
           ContactPointGeneration = "STRUCTURE" >
        <Offset
            x = "14.1285"
            y = "-8.30338"
            z = "35.7917" />
      </Shape>
      <Shape
           Type= "BOX"
           MajorRadius = "78.7873"
           MinorRadius = "9.64181"
           Height = "36.6388"
           ContactPointGeneration = "STRUCTURE" >
        <Offset
            x = "0.417068"
            y = "-8.30338"
            z = "-0.790813" />
      </Shape>
      <Shape
           Type= "BOX"
           MajorRadius = "47.7447"
           MinorRadius = "9.64181"
           Height = "14.5749"
           ContactPointGeneration = "STRUCTURE" >
        <Offset
            x = "31.685"
            y = "-8.30338"
            z = "48.5092" />
      </Shape>
      <Shape
           Type= "BOX"
           MajorRadius = "33.4213"
           MinorRadius = "9.6418"
           Height = "16.9418"
           ContactPointGeneration = "STRUCTURE" >
        <Offset
            x = "46.1706"
            y = "-8.30339"
            z = "61.191" />
      </Shape>
		</Geometry>
	</GameObject>
</AssetDeclaration>