<?xml version="1.0" encoding="UTF-8"?>
<AssetDeclaration xmlns="uri:ea.com:eala:asset" xmlns:xsi="http://www.w3.org/2001/XMLSchema-instance">
	<Includes>
		<Include source="art:fxemperorsrage.xml" type="instance"/>
		<Include source="art:fxabaloneenv.xml" type="instance"/>
	</Includes>
	<FXParticleSystemTemplate ParticleTexture="FXEmperorsRage" PerParticleAttachedSystem="" Priority="ALWAYS_RENDER" SortLevel="1" SystemLifetime="1" Type="GPU_PARTICLE" id="JapanEmperorSpawn_L3">
		<Lifetime High="10" Low="10"/>
		<Size High="120" Low="120"/>
		<BurstCount High="1" Low="1"/>
		<Colors HouseColorSaturation="0">
			<Color Frame="2" RelativeAge="9.999999">
				<Color b="0.070588" g="0.129412" r="0.521569"/>
			</Color>
			<Color Frame="3" RelativeAge="100">
				<Color b="0" g="0" r="0"/>
			</Color>
			<ColorScale High="5" Low="5"/>
		</Colors>
		<Physics>
			<Default>
				<VelocityDamping High="1" Low="1"/>
			</Default>
		</Physics>
		<Draw>
			<Gpu DetailTexture="FXAbaloneEnv" GeometryType="TWO_QUADS" Shader="GpuParticleXY.fx" SpeedMultiplier="1"/>
		</Draw>
		<Volume>
			<Cylinder>
				<Offset x="0" y="0" z="10"/>
			</Cylinder>
		</Volume>
		<Velocity>
			<Ortho>
				<Position>
					<x High="0" Low="0"/>
					<y High="0" Low="0"/>
					<z High="0" Low="0"/>
				</Position>
			</Ortho>
		</Velocity>
		<Event/>
		<Update>
			<Default>
				<SizeRate High="1" Low="1"/>
				<SizeRateDamping High="1" Low="1"/>
				<AngularDampingXY High="1" Low="1"/>
			</Default>
		</Update>
	</FXParticleSystemTemplate>
</AssetDeclaration>