<?xml version="1.0" encoding="UTF-8"?>
<AssetDeclaration xmlns="uri:ea.com:eala:asset" xmlns:xsi="http://www.w3.org/2001/XMLSchema-instance">
	<Includes>
		<Include source="art:fxwaterfall.xml" type="instance"/>
	</Includes>
	<FXParticleSystemTemplate ParticleTexture="FXWaterFall" PerParticleAttachedSystem="" Priority="VERY_LOW_OR_ABOVE" Shader="ALPHA" SortLevel="1" SystemLifetime="5" Type="GPU_PARTICLE" id="SeaWing_Water2">
		<Lifetime High="25" Low="15"/>
		<Size High="15" Low="10"/>
		<BurstCount High="5" Low="5"/>
		<Alphas>
			<Alpha Frame="1" High="0.5" Low="0.5" RelativeAge="0"/>
			<Alpha Frame="2" High="0" Low="0" RelativeAge="100"/>
		</Alphas>
		<Colors HouseColorSaturation="0">
			<Color Frame="1" RelativeAge="0">
				<Color b="1" g="1" r="1"/>
			</Color>
			<Color Frame="2" RelativeAge="100">
				<Color b="1" g="1" r="1"/>
			</Color>
		</Colors>
		<Physics>
			<Default Gravity="-0.0002">
				<VelocityDamping High="0.1" Low="0.1"/>
			</Default>
		</Physics>
		<Draw>
			<Gpu EnableSoftParticles="false" GeometryType="TWO_QUADS" Shader="gpuparticleperpendicularbottom.fx" SpeedMultiplier="1"/>
		</Draw>
		<Volume>
			<Cylinder>
				<Offset x="0" y="0" z="0"/>
			</Cylinder>
		</Volume>
		<Velocity>
			<Ortho>
				<Position>
					<x High="0.1" Low="-0.1"/>
					<y High="0.1" Low="-0.1"/>
					<z High="0.5" Low="0.5"/>
				</Position>
			</Ortho>
		</Velocity>
		<Event/>
		<Update>
			<RenderObject Rotation="ROTATE_AROUND_VELOCITY">
				<AngleX High="7" Low="-7"/>
				<AngularDamping High="1" Low="1"/>
				<StartSize>
					<x High="0" Low="0"/>
					<y High="25" Low="15"/>
					<z High="25" Low="15"/>
				</StartSize>
				<SizeRate>
					<x High="8" Low="4"/>
					<y High="1" Low="1"/>
					<z High="1" Low="1"/>
				</SizeRate>
				<SizeDamping>
					<x High="0.85" Low="0.8"/>
					<y High="0.95" Low="0.95"/>
					<z High="0.95" Low="0.95"/>
				</SizeDamping>
			</RenderObject>
		</Update>
	</FXParticleSystemTemplate>
</AssetDeclaration>