<?xml version="1.0" encoding="us-ascii"?>
<AssetDeclaration xmlns="uri:ea.com:eala:asset" xmlns:xsi="http://www.w3.org/2001/XMLSchema-instance" xmlns:xi="http://www.w3.org/2001/XInclude">
	<Tags></Tags>
	<Includes>
    <Include
		type="all"
		source="ART:JURadarShip_COL.w3x" />
	<Include
		type="all"
		source="ART:JURadarShip_D.xml" />		
    <Include
		type="instance"
		source="DATA:BaseObjects/BaseCollapsingObject.xml" />
	</Includes>
	<GameObject
		id="JapanRadarShip_Collapse"
		inheritFrom="BaseCollapsingObject" 
		EditorName="JapanRadarShip_Collapse">
		<Draws>
			<DynamicsDraw 
			id="ModuleTag_Draw" 
			Collision="NONINTERCOLLIDING"
			FlingPerturbation="20"
			Explodiness="10">
			<ModelConditionState
				ParseCondStateType="PARSE_DEFAULT">
				<Model
					Name="JURadarShip_COL" />
				<Texture
					Original="JURadarShip"
					New="JURadarShip_D" />

				<xi:include
					href="DATA:Includes/VehicleCollapseParticles/JapanVehicleCollapseParticles.xml"
					xpointer="xmlns(n=uri:ea.com:eala:asset) xpointer(/n:JapanVehicleCollapseParticles/child::*)" />
										
			</ModelConditionState>

				<BoneVolumes>

<BoneVolume BoneName="Bone_D_01" Mass="81" Spinniness="3.0" ContactTag="DEBRIS" >
	<Box  HalfSizeX="2.14" HalfSizeY="1.625" HalfSizeZ="1.171" >
		<Translation x="-1.545" y="5.909" z="20.589" />
		<Rotation x="0.0" y="0.0" z="0.0" w="1.0" />
	</Box>
</BoneVolume>
<BoneVolume BoneName="Bone_D_02" Mass="738" Spinniness="3.0" ContactTag="DEBRIS" >
	<Box  HalfSizeX="4.585" HalfSizeY="4.585" HalfSizeZ="1.756" >
		<Translation x="28.343" y="-19.479" z="9.947" />
		<Rotation x="0.0" y="0.0" z="0.0" w="1.0" />
	</Box>
</BoneVolume>
<BoneVolume BoneName="Bone_D_03" Mass="738" Spinniness="3.0" ContactTag="DEBRIS" >
	<Box  HalfSizeX="4.585" HalfSizeY="4.585" HalfSizeZ="1.756" >
		<Translation x="28.343" y="18.922" z="9.947" />
		<Rotation x="0.0" y="0.0" z="0.0" w="1.0" />
	</Box>
</BoneVolume>
<BoneVolume BoneName="Bone_D_04" Mass="1080" Spinniness="3.0" ContactTag="DEBRIS" >
	<Box  HalfSizeX="4.585" HalfSizeY="4.585" HalfSizeZ="2.57" >
		<Translation x="-8.964" y="17.342" z="10.092" />
		<Rotation x="0.0" y="0.0" z="0.0" w="1.0" />
	</Box>
</BoneVolume>
<BoneVolume BoneName="Bone_D_05" Mass="1080" Spinniness="3.0" ContactTag="DEBRIS" >
	<Box  HalfSizeX="4.585" HalfSizeY="4.585" HalfSizeZ="2.57" >
		<Translation x="-8.964" y="-17.51" z="10.092" />
		<Rotation x="0.0" y="0.0" z="0.0" w="1.0" />
	</Box>
</BoneVolume>
<BoneVolume BoneName="Bone_D_06" Mass="54" Spinniness="3.0" ContactTag="DEBRIS" >
	<Box  HalfSizeX="2.197" HalfSizeY="2.197" HalfSizeZ="0.563" >
		<Translation x="13.851" y="5.909" z="14.147" />
		<Rotation x="0.0" y="0.0" z="0.0" w="1.0" />
	</Box>
</BoneVolume>
<BoneVolume BoneName="Bone_D_07" Mass="54" Spinniness="3.0" ContactTag="DEBRIS" >
	<Box  HalfSizeX="2.197" HalfSizeY="2.197" HalfSizeZ="0.563" >
		<Translation x="13.851" y="-5.909" z="14.147" />
		<Rotation x="0.0" y="0.0" z="0.0" w="1.0" />
	</Box>
</BoneVolume>
<BoneVolume BoneName="Bone_D_08" Mass="81" Spinniness="3.0" ContactTag="DEBRIS" >
	<Box  HalfSizeX="2.14" HalfSizeY="1.625" HalfSizeZ="1.171" >
		<Translation x="-1.545" y="-5.909" z="20.589" />
		<Rotation x="0.0" y="0.0" z="0.0" w="1.0" />
	</Box>
</BoneVolume>
<BoneVolume BoneName="Bone_D_09" Mass="2931" Spinniness="3.0" ContactTag="DEBRIS" >
	<Box  HalfSizeX="10.483" HalfSizeY="10.483" HalfSizeZ="1.334" >
		<Translation x="-30.528" y="0.0" z="15.576" />
		<Rotation x="0.0" y="0.0" z="0.0" w="1.0" />
	</Box>
</BoneVolume>
<BoneVolume BoneName="Bone_D_13" Mass="82" Spinniness="3.0" ContactTag="DEBRIS" >
	<Box  HalfSizeX="2.157" HalfSizeY="2.221" HalfSizeZ="0.858" >
		<Translation x="28.374" y="17.693" z="6.233" />
		<Rotation x="0.0" y="0.0" z="0.0" w="1.0" />
	</Box>
</BoneVolume>
<BoneVolume BoneName="Bone_D_11" Mass="13" Spinniness="3.0" ContactTag="DEBRIS" >
	<Box  HalfSizeX="0.564" HalfSizeY="0.277" HalfSizeZ="4.3" >
		<Translation x="-0.28" y="2.987" z="26.725" />
		<Rotation x="0.0" y="0.0" z="0.0" w="1.0" />
	</Box>
</BoneVolume>
<BoneVolume BoneName="Bone_D_12" Mass="13" Spinniness="3.0" ContactTag="DEBRIS" >
	<Box  HalfSizeX="0.564" HalfSizeY="0.277" HalfSizeZ="4.3" >
		<Translation x="-0.28" y="-2.987" z="26.725" />
		<Rotation x="0.0" y="0.0" z="0.0" w="1.0" />
	</Box>
</BoneVolume>
<BoneVolume BoneName="Bone_D_14" Mass="82" Spinniness="3.0" ContactTag="DEBRIS" >
	<Box  HalfSizeX="2.157" HalfSizeY="2.221" HalfSizeZ="0.858" >
		<Translation x="28.374" y="-18.25" z="6.233" />
		<Rotation x="0.0" y="0.0" z="0.0" w="1.0" />
	</Box>
</BoneVolume>
<BoneVolume BoneName="Bone_D_10" Mass="62450" Spinniness="3.0" ContactTag="DEBRIS" >
	<Box  HalfSizeX="38.299" HalfSizeY="12.041" HalfSizeZ="6.771" >
		<Translation x="0.0" y="0.0" z="7.249" />
		<Rotation x="0.0" y="0.0" z="0.0" w="1.0" />
	</Box>
</BoneVolume>




			</BoneVolumes>
			<Lifetime
				Delay="8s"
				FadeTime="8s" />
		</DynamicsDraw>
	</Draws>

	<Behaviors>
		<LifetimeUpdate
			id="ModuleTag_LifeTime"
			MinLifetime="6s"
			MaxLifetime="6s" />	
		<SlowDeath
			id="ModuleTag_Death"
			SinkDelay="1s"
			SinkRate="1.5"
			DestructionDelay="8s">
			<DieMuxData
				DeathTypes="ALL" />
		</SlowDeath>
	</Behaviors>
	
</GameObject>
</AssetDeclaration>