<?xml version="1.0" encoding="utf-8"?>
<AssetDeclaration xmlns="uri:ea.com:eala:asset" xmlns:xsi="http://www.w3.org/2001/XMLSchema-instance">
	<Tags></Tags>
	
	<Includes>
		<Include type="all" source="ART:SA_Fence08.w3x" />
		<Include type="instance" source="DATA:BaseObjects/BaseSimulatedProp.xml" />
		<Include type="instance" source="DATA:GlobalData/GlobalDefines.xml" />
	</Includes>
	
	<GameObject
		id="SA_Fence08"
		inheritFrom="BaseSimulatedProp"
		EditorName="SA_Fence08"
		EditorSorting="DESTRUCTIBLE_PROPS"
		KindOf="=$BASE_CRUSHABLE_OBSTACLE_CLEAR_BY_BUILD_KINDOF"
		Browser="REGION SANTA_MONICA_SM DESTRUCTIBLE_PROPS">
		<Draws>
			<DynamicsDraw
				id="ModuleTag_Draw"
				Collision="NONINTERCOLLIDING"
				Explodiness="0.5"
				InitiallyActive="false">
				<ModelConditionState
					ParseCondStateType="PARSE_DEFAULT">
					<Model
						Name="SA_Fence08" />
				</ModelConditionState>
				<BoneVolumes>
<BoneVolume BoneName="Bone_fence01" Mass="178" Spinniness="3.0" ContactTag="DEBRIS" >
	<Box  HalfSizeX="1.08" HalfSizeY="1.16" HalfSizeZ="7.124" >
		<Translation x="14.223" y="0.048" z="0.0" />
		<Rotation x="0.0" y="0.0" z="0.0" w="1.0" />
	</Box>
</BoneVolume>
<BoneVolume BoneName="Bone_fence02" Mass="178" Spinniness="3.0" ContactTag="DEBRIS" >
	<Box  HalfSizeX="1.08" HalfSizeY="1.16" HalfSizeZ="7.124" >
		<Translation x="-14.928" y="0.048" z="0.0" />
		<Rotation x="0.0" y="0.0" z="0.0" w="1.0" />
	</Box>
</BoneVolume>
<BoneVolume BoneName="Bone_fence03" Mass="56" Spinniness="3.0" ContactTag="DEBRIS" >
	<Box  HalfSizeX="1.192" HalfSizeY="0.452" HalfSizeZ="5.219" >
		<Translation x="-11.848" y="0.048" z="0.0" />
		<Rotation x="0.0" y="0.0" z="0.0" w="1.0" />
	</Box>
</BoneVolume>
<BoneVolume BoneName="Bone_fence04" Mass="287" Spinniness="3.0" ContactTag="DEBRIS" >
	<Box  HalfSizeX="6.098" HalfSizeY="0.452" HalfSizeZ="5.219" >
		<Translation x="-2.289" y="0.048" z="0.0" />
		<Rotation x="0.0" y="0.0" z="0.0" w="1.0" />
	</Box>
</BoneVolume>
<BoneVolume BoneName="Bone_fence05" Mass="104" Spinniness="3.0" ContactTag="DEBRIS" >
	<Box  HalfSizeX="2.193" HalfSizeY="0.452" HalfSizeZ="5.272" >
		<Translation x="8.671" y="0.048" z="0.0" />
		<Rotation x="0.0" y="0.0" z="0.0" w="1.0" />
	</Box>
</BoneVolume>
				</BoneVolumes>
				<Lifetime
					Delay="10s"
					FadeTime="10s" />
			</DynamicsDraw>
		</Draws>
		<Geometry
			IsSmall="false">
<Shape 
     Type= "BOX"
     MajorRadius = "16.0"
     MinorRadius = "3.0"
     Height = "15.0"
     ContactPointGeneration = "NONE" >
    <Offset
        x = "-0.34066"
        y = "0.0795488"
        z = "0.0" />
</Shape>


		</Geometry>
	</GameObject>
</AssetDeclaration>