<CommonFlagDraws xmlns="uri:ea.com:eala:asset" xmlns:xi="http://www.w3.org/2001/XInclude" >

	<ScriptedModelDraw xmlns="uri:ea.com:eala:asset"
		id="ModuleTag_FlagDraw"
		AttachToBoneInAnotherModule="BoneFlag01"
		OkToChangeModelColor="true" >

		<ModelConditionState
			ParseCondStateType="PARSE_DEFAULT" >
			<Model Name="SU_Garrison_Flag" />			
			<Texture
				Original="SU_GarFlag"
				New="NU_GarFlag" />
		</ModelConditionState>
		<AnimationState
			ParseCondStateType="PARSE_DEFAULT">
			<Animation
				AnimationName="SU_Garrison_Flag"
				AnimationMode="LOOP" />			
		</AnimationState>

		<ModelConditionState
			ParseCondStateType="PARSE_NORMAL"
			ConditionsYes="USER_1">
			<Model Name="AU_Garrison_Flag" />
		</ModelConditionState>
		<AnimationState
			ParseCondStateType="PARSE_NORMAL"
			ConditionsYes="USER_1">
			<Animation
				AnimationName="AU_Garrison_Flag"
				AnimationMode="LOOP" />
		</AnimationState>

		<ModelConditionState
			ParseCondStateType="PARSE_NORMAL"
			ConditionsYes="USER_2">
			<Model Name="SU_Garrison_Flag" />
		</ModelConditionState>
		<AnimationState
			ParseCondStateType="PARSE_NORMAL"
			ConditionsYes="USER_2">
			<Animation
				AnimationName="SU_Garrison_Flag"
				AnimationMode="LOOP" />
		</AnimationState>

		<ModelConditionState
			ParseCondStateType="PARSE_NORMAL"
			ConditionsYes="USER_3">
			<Model Name="JU_Garrison_Flag" />
		</ModelConditionState>
		<AnimationState
			ParseCondStateType="PARSE_NORMAL"
			ConditionsYes="USER_3">
			<Animation
				AnimationName="JU_Garrison_Flag"
				AnimationMode="LOOP" />
		</AnimationState>
	</ScriptedModelDraw>
	
</CommonFlagDraws>