<?xml version="1.0" encoding="utf-8"?>
<AssetDeclaration xmlns="uri:ea.com:eala:asset" xmlns:xsi="http://www.w3.org/2001/XMLSchema-instance" xmlns:xi="http://www.w3.org/2001/XInclude">
	<Tags></Tags>
	<Includes>
		<Include type="all" source="DATA:GlobalData/GlobalDefines.xml" /> 

		<Include
			type="all"
			source="ART:JBTechStructure_SKN.w3x" />
		<Include
			type="all"
			source="ART:JBTechStructure_FX.w3x" />			
		<Include
			type="all"
			source="ART:JBTechStructure_BLD.w3x" /> 
		<Include
			type="all"
			source="ART:JBTechStructure_BLD2.w3x" /> 
		<Include
			type="all"
			source="ART:JBTechStructure_Platform_SKN.w3x" />
		<Include
			type="all"
			source="ART:JBTechStructure_Platform_BLD.w3x" />
						
		<!-- Base Object -->
		<Include
			type="instance"
			source="DATA:BaseObjects/BaseStructure.xml" />
	</Includes>
	<GameObject
		id="JapanTechStructure"
		inheritFrom="BaseStructure"
		SelectPortrait="Portrait_JapanTechStructure"
		ButtonImage="Button_JapanTechStructure"
		Side="Japan"
		EditorSorting="STRUCTURE"		
		BuildTime="20"
		CommandSet="JapanTechStructureCommandSet"
		KindOf="+FS_TECHNOLOGY +ACTIVATE_AFTER_UNPACK"
		RadarPriority="STRUCTURE"
		PlacementViewAngle="315d"
		EnergyProduction="-75"
		ProductionQueueType="MAIN_STRUCTURE"
		BuildPlacementTypeFlag="MAIN_STRUCTURE"
		IsTrainable="false"
		EditorName="JapanTechStructure"
		Description="Desc:JapanTechStructure"
		TypeDescription="Type:JapanTechStructure">
		<DisplayName
			xai:joinAction="Replace" xmlns:xai="uri:ea.com:eala:asset:instance">Name:JapanTechStructure</DisplayName>
		<ObjectResourceInfo>
			<BuildCost Account="=$ACCOUNT_ORE" Amount="2000"/>
		</ObjectResourceInfo>
		<ArmorSet
			Armor="BaseFactionStructureArmor"
			DamageFX="FactionStructureDamageFX" />
		<SkirmishAIInformation
			BaseBuildingLocation="BACK">
      <ConstructionBaseSelectionCriteria
        ExcludedBaseTypes="NO_BUILD_RADIUS CAPTURED"
        PreferredBaseTypes="MAIN_BASE"
        SortOrder="PREFER_OLDEST" />
    </SkirmishAIInformation>
		<Draws>
			<ScriptedModelDraw
				id="ModuleTag_Draw"
				OkToChangeModelColor="true"
			  ExtraPublicBone="BONE_CONTACT_POINT_01 BONE_CONTACT_POINT_02 BONE_CONTACT_POINT_03 BONE_CONTACT_POINT_04 BONE_CONTACT_POINT_05 BONE_CONTACT_POINT_06 BONE_CONTACT_POINT_07 BONE_CONTACT_POINT_08 BONE_CONTACT_POINT_09 BONE_CONTACT_POINT_10">
				<ModelConditionState
					ParseCondStateType="PARSE_DEFAULT">
					<Model
						Name="JBTechStructure_SKN" />
				</ModelConditionState>

				<ModelConditionState
					ParseCondStateType="PARSE_NORMAL"
					ConditionsYes="BUILD_PLACEMENT_CURSOR">
					<Model
						Name="JBTechStructure_SKN" />
					<Material ShaderName="ObjectsGeneric.fx" TechniqueName="Default">
						<Constants>
							<Texture Name="DiffuseTexture">
								<Value>JBTechStructure</Value>
							</Texture>
							<Texture Name="NormalMap">
								<Value>JBTechStructure_NRM</Value>
							</Texture>
							<Texture Name="SpecMap">
								<Value>JBTechStructure_SPM</Value>
							</Texture>
							<Float Name="BumpScale">
								<Value>1.000000</Value>
							</Float>
							<Float Name="AmbientColor">
								<Value>0.400000</Value>
								<Value>0.400000</Value>
								<Value>0.400000</Value>
							</Float>
							<Float Name="DiffuseColor">
								<Value>1.000000</Value>
								<Value>1.000000</Value>
								<Value>1.000000</Value>
								<Value>1.000000</Value>
							</Float>
							<Float Name="SpecularColor">
								<Value>0.800000</Value>
								<Value>0.800000</Value>
								<Value>0.800000</Value>
							</Float>
							<Float Name="SpecularExponent">
								<Value>50.000000</Value>
							</Float>
							<Float Name="EnvMult">
								<Value>1.000000</Value>
							</Float>
							<Bool Name="AlphaTestEnable">
								<Value>false</Value>
							</Bool>
						</Constants>
					</Material>						
				</ModelConditionState>				
				<ModelConditionState
					ParseCondStateType="PARSE_NORMAL"
					ConditionsYes="STRUCTURE_UNPACKING">
					<Model
						Name="JBTechStructure_SKN" />
					<Material ShaderName="BasicW3DHolographic.fx" TechniqueName="Default">
						<Constants>
							<Float Name="ColorAmbient">
								<Value>0.000000</Value>
								<Value>0.000000</Value>
								<Value>0.000000</Value>
							</Float>
							<Float Name="ColorDiffuse">
								<Value>0.000000</Value>
								<Value>0.000000</Value>
								<Value>0.000000</Value>
							</Float>
							<Float Name="ColorSpecular">
								<Value>0.000000</Value>
								<Value>0.000000</Value>
								<Value>0.000000</Value>
							</Float>
							<Float Name="Shininess">
								<Value>0.000000</Value>
							</Float>
							<Float Name="ColorEmissive">
								<Value>1.000000</Value>
								<Value>1.000000</Value>
								<Value>1.000000</Value>
							</Float>
							<Texture Name="Texture_0">
								<Value>FXJapanBuildMask</Value>
							</Texture>
							<Bool Name="DepthWriteEnable">
								<Value>false</Value>
							</Bool>
							<Bool Name="AlphaTestEnable">
								<Value>false</Value>
							</Bool>
							<Bool Name="CullingEnable">
								<Value>true</Value>
							</Bool>
							<Int Name="BlendMode">
								<Value>1</Value>
							</Int>
						</Constants>
					</Material>
				</ModelConditionState>
				<ModelConditionState
					ParseCondStateType="PARSE_NORMAL"
					ConditionsYes="SOLD">
					<Model
						Name="JBTechStructure_SKN" />
					<Material ShaderName="BasicW3DHolographic.fx" TechniqueName="Default">
						<Constants>
							<Float Name="ColorAmbient">
								<Value>0.000000</Value>
								<Value>0.000000</Value>
								<Value>0.000000</Value>
							</Float>
							<Float Name="ColorDiffuse">
								<Value>0.000000</Value>
								<Value>0.000000</Value>
								<Value>0.000000</Value>
							</Float>
							<Float Name="ColorSpecular">
								<Value>0.000000</Value>
								<Value>0.000000</Value>
								<Value>0.000000</Value>
							</Float>
							<Float Name="Shininess">
								<Value>0.000000</Value>
							</Float>
							<Float Name="ColorEmissive">
								<Value>1.000000</Value>
								<Value>1.000000</Value>
								<Value>1.000000</Value>
							</Float>
							<Texture Name="Texture_0">
								<Value>FXJapanBuildMask</Value>
							</Texture>
							<Bool Name="DepthWriteEnable">
								<Value>false</Value>
							</Bool>
							<Bool Name="AlphaTestEnable">
								<Value>false</Value>
							</Bool>
							<Bool Name="CullingEnable">
								<Value>true</Value>
							</Bool>
							<Int Name="BlendMode">
								<Value>1</Value>
							</Int>
						</Constants>
					</Material>
				</ModelConditionState>				
				<AnimationState
					ParseCondStateType="PARSE_DEFAULT">					
				</AnimationState>				
				<AnimationState
					ParseCondStateType="PARSE_NORMAL"
					ConditionsYes="STRUCTURE_UNPACKING">
					<Animation
						AnimationName="JBTechStructure_BLD2"
						AnimationMode="MATCH_UNPACKING"
						AnimationBlendTime="0" />
					<Script>
						CurDrawableHideSubObjectPermanently("NewSkin_Fill")
					</Script>							
				</AnimationState>
				<AnimationState
					ParseCondStateType="PARSE_NORMAL"
					ConditionsYes="SOLD"
					Flags="START_FRAME_LAST">
					<Animation
						AnimationName="JBTechStructure_BLD2"
						AnimationMode="ONCE_BACKWARDS"
						AnimationAbsoluteTime="2s"/>
					<Script>
						CurDrawableHideSubObjectPermanently("NewSkin_Fill")
					</Script>						
				</AnimationState>					
			</ScriptedModelDraw>

<!-- DRAW BUILD UP -->

			<ScriptedModelDraw
				id="ModuleTag_Draw_Buildup"
				ExtraPublicBone="BONE_CONTACT_POINT_01 BONE_CONTACT_POINT_02 BONE_CONTACT_POINT_03 BONE_CONTACT_POINT_04 BONE_CONTACT_POINT_05 BONE_CONTACT_POINT_06 BONE_CONTACT_POINT_07 BONE_CONTACT_POINT_08"
				OkToChangeModelColor="true">
				<ModelConditionState
					ParseCondStateType="PARSE_DEFAULT">
					<Model
						Name="" />
				</ModelConditionState>
				<ModelConditionState
					ParseCondStateType="PARSE_NORMAL"
					ConditionsYes="STRUCTURE_UNPACKING">
					<Model
						Name="JBTechStructure_SKN" />
					<Material ShaderName="BuildingsJapanBuildup.fx" TechniqueName="Default">
						<Constants>
							<Texture Name="DiffuseTexture">
								<Value>JBTechStructure</Value>
							</Texture>
							<Texture Name="NormalMap">
								<Value>JBTechStructure_NRM</Value>
							</Texture>
							<Texture Name="SpecMap">
								<Value>JBTechStructure_SPM</Value>
							</Texture>
							<Float Name="EnvMult">
								<Value>1.000000</Value>
							</Float>
							<Bool Name="AlphaTestEnable">
								<Value>true</Value>
							</Bool>
						</Constants>
					</Material>
				</ModelConditionState>
				<ModelConditionState
					ParseCondStateType="PARSE_NORMAL"
					ConditionsYes="SOLD">
					<Model
						Name="JBTechStructure_SKN" />
					<Material ShaderName="BuildingsJapanBuildup.fx" TechniqueName="Default">
						<Constants>
							<Texture Name="DiffuseTexture">
								<Value>JBTechStructure</Value>
							</Texture>
							<Texture Name="NormalMap">
								<Value>JBTechStructure_NRM</Value>
							</Texture>
							<Texture Name="SpecMap">
								<Value>JBTechStructure_SPM</Value>
							</Texture>
							<Float Name="EnvMult">
								<Value>1.000000</Value>
							</Float>
							<Bool Name="AlphaTestEnable">
								<Value>true</Value>
							</Bool>
						</Constants>
					</Material>
				</ModelConditionState>						
				<AnimationState
					ParseCondStateType="PARSE_DEFAULT">
				</AnimationState>
				<AnimationState
					ParseCondStateType="PARSE_NORMAL"
					ConditionsYes="STRUCTURE_UNPACKING">
					<Animation
						AnimationName="JBTechStructure_BLD"
						AnimationMode="MATCH_UNPACKING"
						AnimationBlendTime="0" />
					<Script>
						CurDrawableHideSubObjectPermanently("NewSkin_Fill")
					</Script>							
				</AnimationState>
				<AnimationState
					ParseCondStateType="PARSE_NORMAL"
					ConditionsYes="SOLD"
					Flags="START_FRAME_LAST">
					<Animation
						AnimationName="JBTechStructure_BLD"
						AnimationMode="ONCE_BACKWARDS"
						AnimationAbsoluteTime="2s"/>
					<Script>
						CurDrawableHideSubObjectPermanently("NewSkin_Fill")
					</Script>						
				</AnimationState>				
			</ScriptedModelDraw>

<!-- DRAW PLATFORM -->

			<ScriptedModelDraw
				id="ModuleTag_Draw_Platform"
				OkToChangeModelColor="true">
				<ModelConditionState
					ParseCondStateType="PARSE_DEFAULT">
					<Model
						Name="JBTechStructure_Platform_SKN" />
				</ModelConditionState>
				<ModelConditionState
					ParseCondStateType="PARSE_NORMAL"
					ConditionsYes="OVER_WATER STRUCTURE_UNPACKING">
					<Model
						Name="JBTechStructure_Platform_SKN" />
<!-- particle system template not found							
					<ParticleSysBone
						BoneName="None"
						FXParticleSystemTemplate="ABPowerPlantWakeSplash"
						FollowBone="true" />
-->						
					<Material ShaderName="BasicW3DHolographic.fx" TechniqueName="Default">
						<Constants>
							<Float Name="ColorAmbient">
								<Value>0.000000</Value>
								<Value>0.000000</Value>
								<Value>0.000000</Value>
							</Float>
							<Float Name="ColorDiffuse">
								<Value>0.000000</Value>
								<Value>0.000000</Value>
								<Value>0.000000</Value>
							</Float>
							<Float Name="ColorSpecular">
								<Value>0.000000</Value>
								<Value>0.000000</Value>
								<Value>0.000000</Value>
							</Float>
							<Float Name="Shininess">
								<Value>1.000000</Value>
							</Float>
							<Float Name="ColorEmissive">
								<Value>1.000000</Value>
								<Value>1.000000</Value>
								<Value>1.000000</Value>
							</Float>
							<Texture Name="Texture_0">
								<Value>FXJapanBuildMask</Value>
							</Texture>
							<Bool Name="DepthWriteEnable">
								<Value>true</Value>
							</Bool>
							<Bool Name="AlphaTestEnable">
								<Value>true</Value>
							</Bool>
							<Bool Name="CullingEnable">
								<Value>true</Value>
							</Bool>
							<Int Name="BlendMode">
								<Value>1</Value>
							</Int>
						</Constants>
					</Material>						          
				</ModelConditionState>
				<ModelConditionState
					ParseCondStateType="PARSE_NORMAL"
					ConditionsYes="OVER_WATER SOLD">
					<Model
						Name="JBTechStructure_Platform_SKN" />
<!-- particle system template not found							
					<ParticleSysBone
						BoneName="None"
						FXParticleSystemTemplate="ABPowerPlantWakeSplash"
						FollowBone="true" />
-->						
					<Material ShaderName="BasicW3DHolographic.fx" TechniqueName="Default">
						<Constants>
							<Float Name="ColorAmbient">
								<Value>0.000000</Value>
								<Value>0.000000</Value>
								<Value>0.000000</Value>
							</Float>
							<Float Name="ColorDiffuse">
								<Value>0.000000</Value>
								<Value>0.000000</Value>
								<Value>0.000000</Value>
							</Float>
							<Float Name="ColorSpecular">
								<Value>0.000000</Value>
								<Value>0.000000</Value>
								<Value>0.000000</Value>
							</Float>
							<Float Name="Shininess">
								<Value>1.000000</Value>
							</Float>
							<Float Name="ColorEmissive">
								<Value>1.000000</Value>
								<Value>1.000000</Value>
								<Value>1.000000</Value>
							</Float>
							<Texture Name="Texture_0">
								<Value>FXJapanBuildMask</Value>
							</Texture>
							<Bool Name="DepthWriteEnable">
								<Value>true</Value>
							</Bool>
							<Bool Name="AlphaTestEnable">
								<Value>true</Value>
							</Bool>
							<Bool Name="CullingEnable">
								<Value>true</Value>
							</Bool>
							<Int Name="BlendMode">
								<Value>1</Value>
							</Int>
						</Constants>
					</Material>						          
				</ModelConditionState>				
				<AnimationState
					ParseCondStateType="PARSE_DEFAULT">
					<Script>
						CurDrawableShowSubObjectPermanently("Bib")
						CurDrawableHideSubObjectPermanently("Platform")
						CurDrawableHideSubObjectPermanently("Platform_FX")
					</Script>
				</AnimationState>	
				<AnimationState
					ParseCondStateType="PARSE_NORMAL"  
					ConditionsYes="STRUCTURE_UNPACKING OVER_WATER">
					<Animation
						AnimationName="JBTechStructure_Platform_BLD"
						AnimationMode="MATCH_UNPACKING" />
					<Script>
						CurDrawableHideSubObjectPermanently("Bib")
						CurDrawableShowSubObjectPermanently("Platform")
						CurDrawableShowSubObjectPermanently("Platform_FX")
					</Script>						
					<ParticleSysBone
						BoneName="None"
						FXParticleSystemTemplate="AlliedPowerPlantWaterBuildupFroth"
						FollowBone="true" />
					<ParticleSysBone
						BoneName="None"
						FXParticleSystemTemplate="AlliedPowerPlantWaterBuildupMist"
						FollowBone="true" />
				</AnimationState>
				<AnimationState
					ParseCondStateType="PARSE_NORMAL"
					ConditionsYes="OVER_WATER SOLD"
					Flags="START_FRAME_LAST">
					<Animation
						AnimationName="JBTechStructure_Platform_BLD"
						AnimationMode="ONCE_BACKWARDS"
						AnimationAbsoluteTime="2s"/>
					<Script>
						CurDrawableHideSubObjectPermanently("Bib")
						CurDrawableShowSubObjectPermanently("Platform")
						CurDrawableShowSubObjectPermanently("Platform_FX")
					</Script>						
				</AnimationState>					
				<AnimationState
					ParseCondStateType="PARSE_NORMAL"
					ConditionsYes="OVER_WATER">
					<Script>
						CurDrawableShowSubObjectPermanently("Platform")
						CurDrawableShowSubObjectPermanently("Platform_FX")
						CurDrawableHideSubObjectPermanently("Bib")
					</Script>
				</AnimationState>																				
			</ScriptedModelDraw>

<!-- DRAW BUILD UP PLATFORM -->

			<ScriptedModelDraw
				id="ModuleTag_Draw_Platform_Buildup"
				OkToChangeModelColor="true">
				<ModelConditionState
					ParseCondStateType="PARSE_DEFAULT">
					<Model
						Name="" />
				</ModelConditionState>
				<ModelConditionState
					ParseCondStateType="PARSE_NORMAL"
					ConditionsYes="OVER_WATER STRUCTURE_UNPACKING">
					<Model
						Name="JBTechStructure_Platform_SKN" />
<!-- particle system template not found							
					<ParticleSysBone
						BoneName="None"
						FXParticleSystemTemplate="JBTechStructureWakeSplash"
						FollowBone="true" />
-->						
					<Material ShaderName="BuildingsJapanBuildup.fx" TechniqueName="Default">
						<Constants>
							<Texture Name="DiffuseTexture">
								<Value>JBPlatform</Value>
							</Texture>
							<Texture Name="NormalMap">
								<Value>JBPlatform_NRM</Value>
							</Texture>
							<Texture Name="SpecMap">
								<Value>JBPlatform_SPM</Value>
							</Texture>
							<Float Name="EnvMult">
								<Value>1.000000</Value>
							</Float>
							<Bool Name="AlphaTestEnable">
								<Value>true</Value>
							</Bool>
						</Constants>
					</Material>						          
				</ModelConditionState>
				<ModelConditionState
					ParseCondStateType="PARSE_NORMAL"
					ConditionsYes="OVER_WATER SOLD">
					<Model
						Name="JBTechStructure_Platform_SKN" />
<!-- particle system template not found							
					<ParticleSysBone
						BoneName="None"
						FXParticleSystemTemplate="JBTechStructureWakeSplash"
						FollowBone="true" />
-->						
					<Material ShaderName="BuildingsJapanBuildup.fx" TechniqueName="Default">
						<Constants>
							<Texture Name="DiffuseTexture">
								<Value>JBPlatform</Value>
							</Texture>
							<Texture Name="NormalMap">
								<Value>JBPlatform_NRM</Value>
							</Texture>
							<Texture Name="SpecMap">
								<Value>JBPlatform_SPM</Value>
							</Texture>
							<Float Name="EnvMult">
								<Value>1.000000</Value>
							</Float>
							<Bool Name="AlphaTestEnable">
								<Value>true</Value>
							</Bool>
						</Constants>
					</Material>						          
				</ModelConditionState>				
				<AnimationState
					ParseCondStateType="PARSE_DEFAULT">
					<Script>
						CurDrawableShowSubObjectPermanently("Bib")
						CurDrawableHideSubObjectPermanently("Platform")
						CurDrawableHideSubObjectPermanently("Platform_FX")
					</Script>
				</AnimationState>	
				<AnimationState
					ParseCondStateType="PARSE_NORMAL"  
					ConditionsYes="STRUCTURE_UNPACKING OVER_WATER">
					<Animation
						AnimationName="JBTechStructure_Platform_BLD"
						AnimationMode="MATCH_UNPACKING" />
					<Script>
						CurDrawableHideSubObjectPermanently("Bib")
						CurDrawableShowSubObjectPermanently("Platform")
						CurDrawableShowSubObjectPermanently("Platform_FX")
					</Script>						
				</AnimationState>
				<AnimationState
					ParseCondStateType="PARSE_NORMAL"
					ConditionsYes="OVER_WATER SOLD"
					Flags="START_FRAME_LAST">
					<Animation
						AnimationName="JBTechStructure_Platform_BLD"
						AnimationMode="ONCE_BACKWARDS"
						AnimationAbsoluteTime="2s"/>
					<Script>
						CurDrawableHideSubObjectPermanently("Bib")
						CurDrawableShowSubObjectPermanently("Platform")
						CurDrawableShowSubObjectPermanently("Platform_FX")
					</Script>						
				</AnimationState>					
			</ScriptedModelDraw>		

<!-- DRAW PARTICLES -->

      <ScriptedModelDraw
				id="ModuleTag_Draw_FX"
				OkToChangeModelColor="true">
				<ModelConditionState
					ParseCondStateType="PARSE_DEFAULT">
					<Model
						Name="JBTechStructure_FX" />
				</ModelConditionState>
				<ModelConditionState
					ParseCondStateType="PARSE_NORMAL"
					ConditionsYes="DAMAGED">
					<Model
						Name="JBTechStructure_FX" />
					<ParticleSysBone
						BoneName="FX_BONE01"
						FXParticleSystemTemplate="JapanVehicleDamagedSmoke"
						FollowBone="true" />
					<ParticleSysBone
						BoneName="FX_BONE01"
						FXParticleSystemTemplate="JapanVehicleDamagedSparks"
						FollowBone="true" />
					<ParticleSysBone
						BoneName="FX_BONE01"
						FXParticleSystemTemplate="JapanVehicleDamagedFire"
						FollowBone="true" />
				</ModelConditionState>
				<ModelConditionState
					ParseCondStateType="PARSE_NORMAL"
					ConditionsYes="REALLYDAMAGED">
					<Model
						Name="JBTechStructure_FX" />
					<ParticleSysBone
						BoneName="FX_BONE01"
						FXParticleSystemTemplate="JapanVehicleDamagedSmoke"
						FollowBone="true" />
					<ParticleSysBone
						BoneName="FX_BONE01"
						FXParticleSystemTemplate="JapanVehicleDamagedSparks"
						FollowBone="true" />
					<ParticleSysBone
						BoneName="FX_BONE01"
						FXParticleSystemTemplate="JapanVehicleDamagedFire"
						FollowBone="true" />
					<ParticleSysBone
						BoneName="FX_BONE02"
						FXParticleSystemTemplate="JapanVehicleDamagedSmoke"
						FollowBone="true" />
					<ParticleSysBone
						BoneName="FX_BONE02"
						FXParticleSystemTemplate="JapanVehicleDamagedSparks"
						FollowBone="true" />
					<ParticleSysBone
						BoneName="FX_BONE02"
						FXParticleSystemTemplate="JapanVehicleDamagedFire"
						FollowBone="true" />
					<ParticleSysBone
						BoneName="FX_BONE03"
						FXParticleSystemTemplate="JapanVehicleDamagedSmoke"
						FollowBone="true" />
					<ParticleSysBone
						BoneName="FX_BONE03"
						FXParticleSystemTemplate="JapanVehicleDamagedSparks"
						FollowBone="true" />
					<ParticleSysBone
						BoneName="FX_BONE03"
						FXParticleSystemTemplate="JapanVehicleDamagedFire"
						FollowBone="true" />													
				</ModelConditionState>	
			</ScriptedModelDraw>	
			
<!-- draw for Egg unpacking -->

				<ScriptedModelDraw
				id="ModuleTag_DrawEGG"
				OkToChangeModelColor="true"
				StaticModelLODMode="true">
				<ModelConditionState
					ParseCondStateType="PARSE_DEFAULT">
					<Model
						Name="" />
				</ModelConditionState>
				<ModelConditionState
					ParseCondStateType="PARSE_NORMAL"
					ConditionsYes="STRUCTURE_UNPACKING">
					<Model
						Name="JUEgg_Unpack" />
				</ModelConditionState>
				<ModelConditionState
					ParseCondStateType="PARSE_NORMAL"
					ConditionsYes="SOLD">
					<Model
						Name="" />
				</ModelConditionState>				
				<AnimationState
					ParseCondStateType="PARSE_DEFAULT">
				</AnimationState>
				
				<AnimationState
					ParseCondStateType="PARSE_NORMAL"
					ConditionsYes="STRUCTURE_UNPACKING">
					<Animation
						AnimationName="JUEgg_Unpack"
						AnimationMode="ONCE" />
				</AnimationState>
			</ScriptedModelDraw>						
		</Draws>
		
		<Behaviors>
			<Physics
				id="ModuleTag_Physics"/>

			<BuildingDestructionBehavior
				id="ModuleTag_BuildingDestruction"
				FillerMesh="NEWSKIN_FILL">
				<DieMuxData
					DeathTypes="ALL" 
	        DeathTypesForbidden="SUICIDED"/>
				<Item
					BonePrefix="BONE_CONTACT_POINT_"
					FX="JapanStructureHit"
					CreationObject="AlliedBarracks_Debris"
					FlingVelocity="100.0"/>
			</BuildingDestructionBehavior>
				
			<FXListBehavior
				xai:joinAction="Replace" xmlns:xai="uri:ea.com:eala:asset:instance" id="ModuleTag_FXList">
				<DieMuxData
					DeathTypes="ALL"
					DeathTypesForbidden="SUICIDED" />
				<Event
					Index="onDeath"
					FX="FX_YU_Hotel02_Explode" />
			</FXListBehavior>
			<FXListBehavior xai:joinAction="Replace" xmlns:xai="uri:ea.com:eala:asset:instance" id="ModuleTag_DieSound">
				<DieMuxData DeathTypes="ALL" DeathTypesForbidden="SUICIDED" />
					<Event Index="onDeath" FX="FX_LargeBuildingDieExplosion" />
			</FXListBehavior>
			<CreateObjectDie
				id="ModuleTag_CreateObjectDie"
				CreationList="JBTechStructure_Die_OCL">
				<DieMuxData
					DeathTypes="ALL"
					DeathTypesForbidden="SUICIDED"
					ExemptStatus="OVER_WATER" />
			</CreateObjectDie>
			<CreateObjectDie
				id="ModuleTag_Platform_CreateObjectDie"
				CreationList="JBTechStructure_Platform_Die_OCL">
				<DieMuxData
					DeathTypes="ALL"
					DeathTypesForbidden="SUICIDED"
					RequiredStatus="OVER_WATER" />
			</CreateObjectDie>
			<DestroyDie
				id="ModuleTag_Die">
				<DieMuxData
					DeathTypes="ALL"
					DeathTypesForbidden="SUICIDED" />
			</DestroyDie>				
	
			<StructureUnpackUpdate
				id="ModuleTag_StructureUnpackUpdate"
				UnpackTime="30s" />
			<xi:include
				href="../../Includes/GenericBuildingRepair.xml" />
			<xi:include
				href="../../Includes/GenericEngineerContain.xml" />
			<xi:include
				href="../../Includes/GenericJapanBuildingDestruction.xml" />
			<xi:include
				href="../../Includes/GenericJapanBuildingSuicide.xml" />
			<xi:include
				href="DATA:Includes/InfiltratorContainParalyze.xml" />									
			<LUAEventList
				id="ModuleTag_LUAEventList"
				EventListName="BuildingPowerFunctions"/>				
		</Behaviors>
		<AI>
			<AIUpdate
				id="ModuleTag_AIUpdate"
				AutoAcquireEnemiesWhenIdle="NO"
				StateMachine="StructureAIStateMachine">
			</AIUpdate>
		</AI>
		<Body>
			<ActiveBody
				id="ModuleTag_Body"
				MaxHealth="2000.0" />
		</Body>
		<Geometry>
			<Shape
				 Type= "BOX"
				 MajorRadius = "60.0"
				 MinorRadius = "45.0"
				 Height = "5.0" >
				<Offset
					x = "0.0"
					y = "0.0"
					z = "0.0" />
			</Shape>
<Shape 
     Type= "BOX"
     MajorRadius = "28.1816"
     MinorRadius = "15.6535"
     Height = "16.3646"
     ContactPointGeneration = "STRUCTURE" >
    <Offset
        x = "31.5561"
        y = "-13.9533"
        z = "0.0" />
</Shape>
<Shape 
     Type= "BOX"
     MajorRadius = "30.1792"
     MinorRadius = "29.9114"
     Height = "50.1655"
     ContactPointGeneration = "STRUCTURE" >
    <Offset
        x = "-15.262"
        y = "0.0"
        z = "0.0" />
</Shape>
<Shape 
     Type= "BOX"
     MajorRadius = "20.0"
     MinorRadius = "20.0"
     Height = "100.0"
     ContactPointGeneration = "STRUCTURE" >
    <Offset
        x = "-15.262"
        y = "0.0"
        z = "0.0" />
</Shape>
<Shape 
     Type= "BOX"
     MajorRadius = "10.0"
     MinorRadius = "10.0"
     Height = "130.0"
     ContactPointGeneration = "STRUCTURE" >
    <Offset
        x = "-15.262"
        y = "0.0"
        z = "0.0" />
</Shape>
		</Geometry>
		<ClientBehaviors>
			<ModelConditionAudioLoopClientBehavior xai:joinAction="Replace" xmlns:xai="uri:ea.com:eala:asset:instance" id="ModuleTag_StructureConstructionAudio">
				<ModelConditionSound
					Sound="JAP_Nanocore_DeployStructureLand"
					RequiredFlags="STRUCTURE_UNPACKING"
					ExcludedFlags="OVER_WATER"/>
				<ModelConditionSound
					Sound="JAP_Nanocore_DeployStructureWaterMS"
					RequiredFlags="STRUCTURE_UNPACKING OVER_WATER"/>
			</ModelConditionAudioLoopClientBehavior>
		</ClientBehaviors>
		<AudioArrayVoice>
			<AudioEntry Sound="JAP_TechCenter_SelectMS" AudioType="voiceSelect" />
		</AudioArrayVoice>
		<AudioArraySound>
		<AudioEntry Sound="JAP_Nanocore_DeployLoop" AudioType="soundUnderConstruction" />
<!--
			<AudioEntry Sound="HumanFaction_MediumBuilding_LightDamageMS" AudioType="soundOnDamaged" />
			<AudioEntry Sound="HumanFaction_MediumBuilding_HeavyDamageMS" AudioType="soundOnReallyDamaged" />
-->
		</AudioArraySound>
		<VisionInfo
			VisionRange="150"
			ShroudClearingRange="500" />
		<ProjectedBuildabilityInfo
			Radius="120"
			RadiusY="105"
			BuildPlacementTypes="OTHER_STRUCTURE" />	
			
	</GameObject>
</AssetDeclaration>
